ptyx/__init__.py
ptyx/asynctools.py
ptyx/compilation.py
ptyx/compilation_options.py
ptyx/config.py
ptyx/context.py
ptyx/errors.py
ptyx/extensions/__init__.py
ptyx/extensions/extended_python/__init__.py
ptyx/extensions/extended_python/tests/test_extended_python.py
ptyx/extensions/geoptyx/__init__.py
ptyx/extensions/geoptyx/tests/test_geoptyx.py
ptyx/extensions/questions/__init__.py
ptyx/extensions/questions/tests/in.txt
ptyx/extensions/questions/tests/out.ptyx
ptyx/extensions/questions/tests/test_questions.py
ptyx/internal_types.py
ptyx/latex_generator.py
ptyx/printers.py
ptyx/py.typed
ptyx/randfunc.py
ptyx/script.py
ptyx/shell.py
ptyx/syntax_tree.py
ptyx/sys_info.py
ptyx/utilities.py
ptyx-29.2.0.dist-info/LICENSE
ptyx-29.2.0.dist-info/METADATA
ptyx-29.2.0.dist-info/WHEEL
ptyx-29.2.0.dist-info/entry_points.txt
ptyx-29.2.0.dist-info/RECORD
