Metadata-Version: 2.1
Name: ptyx
Version: 29.2.0
Summary: pTyX is a python precompiler for LaTeX.
Home-page: https://github.com/wxgeo/ptyx
License: GPL-3.0-or-later
Keywords: python,tikz,latex,pdf,exam,mcq,student
Author: Nicolas Pourcelot
Author-email: nicolas.pourcelot@gmail.com
Requires-Python: >=3.10,<4.0
Classifier: License :: OSI Approved :: GNU General Public License v3 or later (GPLv3+)
Classifier: Programming Language :: Python :: 3
Classifier: Programming Language :: Python :: 3.10
Classifier: Programming Language :: Python :: 3.11
Classifier: Programming Language :: Python :: 3.12
Requires-Dist: numpy (>=2.1.3,<3.0.0)
Requires-Dist: psutil (>=5.9.4)
Requires-Dist: pymupdf (>=1.21.1)
Requires-Dist: sympy (>=1.10.1,<2.0.0)
Project-URL: Repository, https://github.com/wxgeo/ptyx
